square_root_lib/__init__.py
square_root_lib/__main__.py
square_root_lib/core.py
squarerootlib-0.1.0.dist-info/licenses/LICENSE
squarerootlib-0.1.0.dist-info/METADATA
squarerootlib-0.1.0.dist-info/WHEEL
squarerootlib-0.1.0.dist-info/entry_points.txt
squarerootlib-0.1.0.dist-info/top_level.txt
squarerootlib-0.1.0.dist-info/RECORD
