Metadata-Version: 2.4
Name: SquareRootLib
Version: 0.1.0
Summary: Calculate the square root of a number
Author: Your Name
Author-email: Your Name <you@example.com>
License: MIT License
Requires-Python: >=3.7
License-File: LICENSE
Dynamic: author
Dynamic: license-file
Dynamic: requires-python
